Metadata-Version: 1.0
Name: marcosdistributions
Version: 0.1
Summary: Gaussian and Binomial distributions
Home-page: UNKNOWN
Author: Marco Besier
Author-email: marcobesier@hey.com
License: UNKNOWN
Platform: UNKNOWN
